[{"data": {"id": "pRNFL", "value": "pRNFL", "name": "pRNFL", "degree": 12, "node_color": "#d94635", "font_color": "white", "borderSize": 2, "borderColor": "black", "diameter": 60}, "position": {"x": -70.07412295010629, "y": 269.7500018509273}}, {"data": {"id": "pRNFL Change", "value": "pRNFL Change", "name": "pRNFL\nChange", "degree": 6, "node_color": "#fff5f0", "font_color": "black", "borderSize": 2, "borderColor": "black", "diameter": 60}, "position": {"x": 2.4716050229121715, "y": 266.81033650530685}}, {"data": {"id": "tpRNFL", "value": "tpRNFL", "name": "tRNFL", "degree": 8, "node_color": "#fee4d8", "font_color": "black", "borderSize": 2, "borderColor": "black", "diameter": 60}, "position": {"x": -102.90073513161481, "y": 333.4963314128687}}, {"data": {"id": "INL", "value": "INL", "name": "INL", "degree": 14, "node_color": "#990c13", "font_color": "white", "borderSize": 2, "borderColor": "black", "diameter": 60}, "position": {"x": 77.91047685744283, "y": 398.8297975724639}}, {"data": {"id": "INL Change", "value": "INL Change", "name": "INL\nChange", "degree": 9, "node_color": "#fdc9b8", "font_color": "black", "borderSize": 2, "borderColor": "black", "diameter": 60}, "position": {"x": 146.6631850556219, "y": 399.5264675606056}}, {"data": {"id": "NWMV", "value": "NWMV", "name": "NWMV", "degree": 11, "node_color": "#fa694a", "font_color": "black", "borderSize": 2, "borderColor": "black", "diameter": 60}, "position": {"x": 5.895823818309099, "y": 520.038256322119}}, {"data": {"id": "ORL", "value": "ORL", "name": "ORL", "degree": 16, "node_color": "#67000d", "font_color": "white", "borderSize": 2, "borderColor": "black", "diameter": 60}, "position": {"x": -170.8425889260941, "y": 455.48898759011513}}, {"data": {"id": "mRNFL Change", "value": "mRNFL Change", "name": "mRNFL\nChange", "degree": 11, "node_color": "#fa694a", "font_color": "black", "borderSize": 2, "borderColor": "black", "diameter": 60}, "position": {"x": -175.05931648580236, "y": 335.50850632990034}}, {"data": {"id": "TRT", "value": "TRT", "name": "TRT", "degree": 15, "node_color": "#7f0610", "font_color": "white", "borderSize": 2, "borderColor": "black", "diameter": 60}, "position": {"x": 117.45769616821732, "y": 334.78567045931067}}, {"data": {"id": "TMV", "value": "TMV", "name": "TMV", "degree": 15, "node_color": "#7f0610", "font_color": "white", "borderSize": 2, "borderColor": "black", "diameter": 60}, "position": {"x": -24.904587166540516, "y": 336.83357687193626}}, {"data": {"id": "T2LV Change", "value": "T2LV Change", "name": "T2LV\nChange", "degree": 7, "node_color": "#ffede4", "font_color": "black", "borderSize": 2, "borderColor": "black", "diameter": 60}, "position": {"x": 186.3369026259113, "y": 457.7069117204861}}, {"data": {"id": "T2LC Change", "value": "T2LC Change", "name": "T2LC\nChange", "degree": 8, "node_color": "#fee4d8", "font_color": "black", "borderSize": 2, "borderColor": "black", "diameter": 60}, "position": {"x": 42.260327432137544, "y": 452.9543796501251}}, {"data": {"id": "NBV", "value": "NBV", "name": "NBV", "degree": 14, "node_color": "#990c13", "font_color": "white", "borderSize": 2, "borderColor": "black", "diameter": 60}, "position": {"x": -142.57484676705008, "y": 520.6429543532372}}, {"data": {"id": "TRT Change", "value": "TRT Change", "name": "TRT\nChange", "degree": 9, "node_color": "#fdc9b8", "font_color": "black", "borderSize": 2, "borderColor": "black", "diameter": 60}, "position": {"x": -136.1532470447371, "y": 391.3111875720196}}, {"data": {"id": "TMV Change", "value": "TMV Change", "name": "TMV\nChange", "degree": 9, "node_color": "#fdc9b8", "font_color": "black", "borderSize": 2, "borderColor": "black", "diameter": 60}, "position": {"x": 42.05867862225685, "y": 332.5785262852045}}, {"data": {"id": "T2LV", "value": "T2LV", "name": "T2LV", "degree": 9, "node_color": "#fdc9b8", "font_color": "black", "borderSize": 2, "borderColor": "black", "diameter": 60}, "position": {"x": 110.44970891988581, "y": 457.999997182553}}, {"data": {"id": "NGMV Change", "value": "NGMV Change", "name": "NGMV\nChange", "degree": 8, "node_color": "#fee4d8", "font_color": "black", "borderSize": 2, "borderColor": "black", "diameter": 60}, "position": {"x": 43.40919145488148, "y": 576.9907856193554}}, {"data": {"id": "NGMV", "value": "NGMV", "name": "NGMV", "degree": 10, "node_color": "#fc9980", "font_color": "black", "borderSize": 2, "borderColor": "black", "diameter": 60}, "position": {"x": 155.0879170953361, "y": 518.738852512355}}, {"data": {"id": "mRNFL", "value": "mRNFL", "name": "mRNFL", "degree": 15, "node_color": "#7f0610", "font_color": "white", "borderSize": 2, "borderColor": "black", "diameter": 60}, "position": {"x": 72.55645993706501, "y": 273.84597754169425}}, {"data": {"id": "ORL Change", "value": "ORL Change", "name": "ORL\nChange", "degree": 9, "node_color": "#fdc9b8", "font_color": "black", "borderSize": 2, "borderColor": "black", "diameter": 60}, "position": {"x": -99.7496116552036, "y": 451.26210212957506}}, {"data": {"id": "NBV Change", "value": "NBV Change", "name": "NBV\nChange", "degree": 9, "node_color": "#fdc9b8", "font_color": "black", "borderSize": 2, "borderColor": "black", "diameter": 60}, "position": {"x": -65.3135734835509, "y": 519.4144227514419}}, {"data": {"id": "NWMV Change", "value": "NWMV Change", "name": "NWMV\nChange", "degree": 11, "node_color": "#fa694a", "font_color": "black", "borderSize": 2, "borderColor": "black", "diameter": 60}, "position": {"x": 82.00111873366455, "y": 516.8411362491438}}, {"data": {"id": "GCIPL Change", "value": "GCIPL Change", "name": "GCIPL\nChange", "degree": 12, "node_color": "#d94635", "font_color": "white", "borderSize": 2, "borderColor": "black", "diameter": 60}, "position": {"x": 2.2685669974540903, "y": 393.1233714855867}}, {"data": {"id": "GCIPL", "value": "GCIPL", "name": "GCIPL", "degree": 14, "node_color": "#990c13", "font_color": "white", "borderSize": 2, "borderColor": "black", "diameter": 60}, "position": {"x": -60.55199762351715, "y": 396.9607887518223}}, {"data": {"id": "T2LC", "value": "T2LC", "name": "T2LC", "degree": 9, "node_color": "#fdc9b8", "font_color": "black", "borderSize": 2, "borderColor": "black", "diameter": 60}, "position": {"x": -29.131219341910423, "y": 457.3105363752571}}, {"data": {"source": "pRNFL", "target": "mRNFL", "weight": 0.51431947964217, "edge_color": "rgb(124,124,124)", "edge_trans": 0.508591721841499, "edge_thick": 2.5429586092074947}}, {"data": {"source": "pRNFL", "target": "tpRNFL", "weight": 0.6514445971022812, "edge_color": "rgb(89,89,89)", "edge_trans": 0.5908668013974475, "edge_thick": 2.9543340069872372}}, {"data": {"source": "pRNFL", "target": "TMV", "weight": 0.4691982337298587, "edge_color": "rgb(135,135,135)", "edge_trans": 0.48151897130636223, "edge_thick": 2.4075948565318113}}, {"data": {"source": "pRNFL", "target": "TRT", "weight": 0.46920448647066415, "edge_color": "rgb(135,135,135)", "edge_trans": 0.4815227229512596, "edge_thick": 2.407613614756298}}, {"data": {"source": "pRNFL", "target": "GCIPL", "weight": 0.4274366913884233, "edge_color": "rgb(146,146,146)", "edge_trans": 0.4564620431362172, "edge_thick": 2.282310215681086}}, {"data": {"source": "pRNFL", "target": "INL", "weight": 0.4014915473993704, "edge_color": "rgb(153,153,153)", "edge_trans": 0.4408949550248009, "edge_thick": 2.2044747751240044}}, {"data": {"source": "pRNFL", "target": "INL Change", "weight": 0.16796904093441178, "edge_color": "rgb(211,211,211)", "edge_trans": 0.3007814356828911, "edge_thick": 1.5039071784144555}}, {"data": {"source": "pRNFL", "target": "T2LC", "weight": -0.18798441419578266, "edge_color": "rgb(255,255,255)", "edge_trans": 0.2, "edge_thick": 1.0}}, {"data": {"source": "pRNFL", "target": "T2LV", "weight": -0.19148952486245915, "edge_color": "rgb(255,255,255)", "edge_trans": 0.2, "edge_thick": 1.0}}, {"data": {"source": "pRNFL", "target": "NBV", "weight": 0.2121721507289985, "edge_color": "rgb(201,201,201)", "edge_trans": 0.32730330448659783, "edge_thick": 1.6365165224329892}}, {"data": {"source": "pRNFL", "target": "NGMV", "weight": 0.23853372369730733, "edge_color": "rgb(194,194,194)", "edge_trans": 0.34312025001314195, "edge_thick": 1.7156012500657098}}, {"data": {"source": "pRNFL", "target": "NGMV Change", "weight": -0.16049625237128065, "edge_color": "rgb(255,255,255)", "edge_trans": 0.2, "edge_thick": 1.0}}, {"data": {"source": "pRNFL Change", "target": "tpRNFL", "weight": -0.14797576647844796, "edge_color": "rgb(255,255,255)", "edge_trans": 0.2, "edge_thick": 1.0}}, {"data": {"source": "pRNFL Change", "target": "TMV Change", "weight": 0.1888715887994231, "edge_color": "rgb(207,207,207)", "edge_trans": 0.31332296578598173, "edge_thick": 1.5666148289299087}}, {"data": {"source": "pRNFL Change", "target": "TRT Change", "weight": 0.18865043893658245, "edge_color": "rgb(207,207,207)", "edge_trans": 0.3131902758536337, "edge_thick": 1.5659513792681685}}, {"data": {"source": "pRNFL Change", "target": "INL", "weight": 0.17022304435061547, "edge_color": "rgb(211,211,211)", "edge_trans": 0.3021338378818645, "edge_thick": 1.5106691894093225}}, {"data": {"source": "pRNFL Change", "target": "INL Change", "weight": 0.22594605593364347, "edge_color": "rgb(198,198,198)", "edge_trans": 0.3355676485214382, "edge_thick": 1.677838242607191}}, {"data": {"source": "pRNFL Change", "target": "T2LC Change", "weight": -0.24303813157790363, "edge_color": "rgb(255,255,255)", "edge_trans": 0.2, "edge_thick": 1.0}}, {"data": {"source": "tpRNFL", "target": "mRNFL", "weight": 0.17506505419275367, "edge_color": "rgb(211,211,211)", "edge_trans": 0.3050390441077661, "edge_thick": 1.5251952205388304}}, {"data": {"source": "tpRNFL", "target": "TMV", "weight": 0.5325182432278384, "edge_color": "rgb(119,119,119)", "edge_trans": 0.51951098119795, "edge_thick": 2.59755490598975}}, {"data": {"source": "tpRNFL", "target": "TRT", "weight": 0.5325498968263005, "edge_color": "rgb(119,119,119)", "edge_trans": 0.5195299733591233, "edge_thick": 2.5976498667956163}}, {"data": {"source": "tpRNFL", "target": "GCIPL", "weight": 0.511421068964975, "edge_color": "rgb(125,125,125)", "edge_trans": 0.5068526752432608, "edge_thick": 2.5342633762163036}}, {"data": {"source": "tpRNFL", "target": "ORL", "weight": 0.40466518907425714, "edge_color": "rgb(152,152,152)", "edge_trans": 0.44279914023987893, "edge_thick": 2.2139957011993943}}, {"data": {"source": "tpRNFL", "target": "ORL Change", "weight": -0.18165498297630078, "edge_color": "rgb(255,255,255)", "edge_trans": 0.2, "edge_thick": 1.0}}, {"data": {"source": "INL", "target": "mRNFL", "weight": 0.4039547738033378, "edge_color": "rgb(152,152,152)", "edge_trans": 0.44237289103028643, "edge_thick": 2.211864455151432}}, {"data": {"source": "INL", "target": "mRNFL Change", "weight": -0.16906029842950063, "edge_color": "rgb(255,255,255)", "edge_trans": 0.2, "edge_thick": 1.0}}, {"data": {"source": "INL", "target": "TMV", "weight": 0.14961174367248814, "edge_color": "rgb(217,217,217)", "edge_trans": 0.2897670561101895, "edge_thick": 1.4488352805509472}}, {"data": {"source": "INL", "target": "TRT", "weight": 0.149602726254272, "edge_color": "rgb(217,217,217)", "edge_trans": 0.2897616456586627, "edge_thick": 1.4488082282933132}}, {"data": {"source": "INL", "target": "GCIPL Change", "weight": 0.2857846992552621, "edge_color": "rgb(182,182,182)", "edge_trans": 0.37147083847668716, "edge_thick": 1.8573541923834356}}, {"data": {"source": "INL", "target": "INL Change", "weight": 0.15652058517788148, "edge_color": "rgb(215,215,215)", "edge_trans": 0.29391236147090155, "edge_thick": 1.4695618073545078}}, {"data": {"source": "INL", "target": "ORL", "weight": -0.2004656650548739, "edge_color": "rgb(255,255,255)", "edge_trans": 0.2, "edge_thick": 1.0}}, {"data": {"source": "INL", "target": "T2LC", "weight": -0.15133813515196012, "edge_color": "rgb(255,255,255)", "edge_trans": 0.2, "edge_thick": 1.0}}, {"data": {"source": "INL", "target": "T2LV", "weight": -0.1996901452547503, "edge_color": "rgb(255,255,255)", "edge_trans": 0.2, "edge_thick": 1.0}}, {"data": {"source": "INL", "target": "NWMV", "weight": -0.15193269376163204, "edge_color": "rgb(255,255,255)", "edge_trans": 0.2, "edge_thick": 1.0}}, {"data": {"source": "INL", "target": "NWMV Change", "weight": 0.14351137703255268, "edge_color": "rgb(219,219,219)", "edge_trans": 0.2861068357222861, "edge_thick": 1.4305341786114303}}, {"data": {"source": "INL", "target": "NGMV", "weight": 0.2842093160927112, "edge_color": "rgb(183,183,183)", "edge_trans": 0.37052560847484095, "edge_thick": 1.8526280423742048}}, {"data": {"source": "INL Change", "target": "mRNFL", "weight": 0.32425997362330095, "edge_color": "rgb(172,172,172)", "edge_trans": 0.39455600564519056, "edge_thick": 1.9727800282259529}}, {"data": {"source": "INL Change", "target": "mRNFL Change", "weight": -0.41534801505235214, "edge_color": "rgb(255,255,255)", "edge_trans": 0.2, "edge_thick": 1.0}}, {"data": {"source": "INL Change", "target": "GCIPL Change", "weight": -0.17876535449207737, "edge_color": "rgb(255,255,255)", "edge_trans": 0.2, "edge_thick": 1.0}}, {"data": {"source": "INL Change", "target": "T2LC Change", "weight": -0.22750229194671648, "edge_color": "rgb(255,255,255)", "edge_trans": 0.2, "edge_thick": 1.0}}, {"data": {"source": "INL Change", "target": "T2LV", "weight": -0.14056040577960863, "edge_color": "rgb(255,255,255)", "edge_trans": 0.2, "edge_thick": 1.0}}, {"data": {"source": "INL Change", "target": "NGMV", "weight": 0.15516265570664867, "edge_color": "rgb(216,216,216)", "edge_trans": 0.29309760369824517, "edge_thick": 1.4654880184912258}}, {"data": {"source": "NWMV", "target": "TMV", "weight": 0.19261235752984993, "edge_color": "rgb(206,206,206)", "edge_trans": 0.3155674272719367, "edge_thick": 1.5778371363596835}}, {"data": {"source": "NWMV", "target": "TRT", "weight": 0.19258677489368292, "edge_color": "rgb(206,206,206)", "edge_trans": 0.31555207768854254, "edge_thick": 1.5777603884427127}}, {"data": {"source": "NWMV", "target": "GCIPL", "weight": 0.26239311226624273, "edge_color": "rgb(188,188,188)", "edge_trans": 0.3574358847343774, "edge_thick": 1.7871794236718865}}, {"data": {"source": "NWMV", "target": "ORL", "weight": 0.2049808220552109, "edge_color": "rgb(203,203,203)", "edge_trans": 0.322988506806144, "edge_thick": 1.6149425340307197}}, {"data": {"source": "NWMV", "target": "T2LC", "weight": -0.20760265886692778, "edge_color": "rgb(255,255,255)", "edge_trans": 0.2, "edge_thick": 1.0}}, {"data": {"source": "NWMV", "target": "T2LC Change", "weight": 0.19023524793798152, "edge_color": "rgb(207,207,207)", "edge_trans": 0.3141411613594129, "edge_thick": 1.5707058067970645}}, {"data": {"source": "NWMV", "target": "NBV", "weight": 0.7099636367712514, "edge_color": "rgb(73,73,73)", "edge_trans": 0.6259782290737284, "edge_thick": 3.1298911453686418}}, {"data": {"source": "NWMV", "target": "NBV Change", "weight": -0.6794030011893852, "edge_color": "rgb(255,255,255)", "edge_trans": 0.2, "edge_thick": 1.0}}, {"data": {"source": "NWMV", "target": "NWMV Change", "weight": -0.7850452457313543, "edge_color": "rgb(255,255,255)", "edge_trans": 0.2, "edge_thick": 1.0}}, {"data": {"source": "NWMV", "target": "NGMV Change", "weight": 0.4158396394935201, "edge_color": "rgb(149,149,149)", "edge_trans": 0.4495038112313645, "edge_thick": 2.247519056156823}}, {"data": {"source": "ORL", "target": "mRNFL", "weight": -0.13409430423207028, "edge_color": "rgb(255,255,255)", "edge_trans": 0.2, "edge_thick": 1.0}}, {"data": {"source": "ORL", "target": "mRNFL Change", "weight": 0.2090799152244876, "edge_color": "rgb(202,202,202)", "edge_trans": 0.3254479629791357, "edge_thick": 1.6272398148956784}}, {"data": {"source": "ORL", "target": "TMV", "weight": 0.7874486955183231, "edge_color": "rgb(54,54,54)", "edge_trans": 0.6724692694527248, "edge_thick": 3.3623463472636237}}, {"data": {"source": "ORL", "target": "TMV Change", "weight": -0.26300945082116567, "edge_color": "rgb(255,255,255)", "edge_trans": 0.2, "edge_thick": 1.0}}, {"data": {"source": "ORL", "target": "TRT", "weight": 0.7874611747899298, "edge_color": "rgb(54,54,54)", "edge_trans": 0.6724767570165153, "edge_thick": 3.362383785082576}}, {"data": {"source": "ORL", "target": "TRT Change", "weight": -0.26302821438310875, "edge_color": "rgb(255,255,255)", "edge_trans": 0.2, "edge_thick": 1.0}}, {"data": {"source": "ORL", "target": "GCIPL", "weight": 0.6304276066694825, "edge_color": "rgb(94,94,94)", "edge_trans": 0.5782566057461065, "edge_thick": 2.8912830287305322}}, {"data": {"source": "ORL", "target": "GCIPL Change", "weight": -0.20420069933481455, "edge_color": "rgb(255,255,255)", "edge_trans": 0.2, "edge_thick": 1.0}}, {"data": {"source": "ORL", "target": "ORL Change", "weight": -0.24995009214395514, "edge_color": "rgb(255,255,255)", "edge_trans": 0.2, "edge_thick": 1.0}}, {"data": {"source": "ORL", "target": "T2LV", "weight": 0.1322764502281825, "edge_color": "rgb(222,222,222)", "edge_trans": 0.27936587889573167, "edge_thick": 1.3968293944786583}}, {"data": {"source": "ORL", "target": "T2LV Change", "weight": 0.14610048725298078, "edge_color": "rgb(218,218,218)", "edge_trans": 0.2876603020259836, "edge_thick": 1.4383015101299177}}, {"data": {"source": "ORL", "target": "NWMV Change", "weight": -0.1811737244195289, "edge_color": "rgb(255,255,255)", "edge_trans": 0.2, "edge_thick": 1.0}}, {"data": {"source": "ORL", "target": "NGMV", "weight": -0.21724563587869825, "edge_color": "rgb(255,255,255)", "edge_trans": 0.2, "edge_thick": 1.0}}, {"data": {"source": "mRNFL Change", "target": "mRNFL", "weight": -0.3083870750439688, "edge_color": "rgb(255,255,255)", "edge_trans": 0.2, "edge_thick": 1.0}}, {"data": {"source": "mRNFL Change", "target": "TMV Change", "weight": 0.20389441152288906, "edge_color": "rgb(203,203,203)", "edge_trans": 0.3223366604148131, "edge_thick": 1.6116833020740653}}, {"data": {"source": "mRNFL Change", "target": "TRT Change", "weight": 0.20370856580560529, "edge_color": "rgb(203,203,203)", "edge_trans": 0.3222251529721369, "edge_thick": 1.6111257648606843}}, {"data": {"source": "mRNFL Change", "target": "GCIPL", "weight": 0.1646374634180098, "edge_color": "rgb(213,213,213)", "edge_trans": 0.2987824889524461, "edge_thick": 1.4939124447622303}}, {"data": {"source": "mRNFL Change", "target": "GCIPL Change", "weight": -0.17341213664602828, "edge_color": "rgb(255,255,255)", "edge_trans": 0.2, "edge_thick": 1.0}}, {"data": {"source": "mRNFL Change", "target": "ORL Change", "weight": -0.24302721013740058, "edge_color": "rgb(255,255,255)", "edge_trans": 0.2, "edge_thick": 1.0}}, {"data": {"source": "mRNFL Change", "target": "NWMV Change", "weight": -0.1763408062971066, "edge_color": "rgb(255,255,255)", "edge_trans": 0.2, "edge_thick": 1.0}}, {"data": {"source": "mRNFL Change", "target": "NGMV Change", "weight": 0.14821597852038843, "edge_color": "rgb(218,218,218)", "edge_trans": 0.2889295969265076, "edge_thick": 1.444647984632538}}, {"data": {"source": "TRT", "target": "mRNFL", "weight": 0.38989552512678727, "edge_color": "rgb(156,156,156)", "edge_trans": 0.4339373408934084, "edge_thick": 2.1696867044670416}}, {"data": {"source": "TRT", "target": "TMV", "weight": 0.9999998896399527, "edge_color": "rgb(0,0,0)", "edge_trans": 0.8, "edge_thick": 4.0}}, {"data": {"source": "TRT", "target": "TMV Change", "weight": -0.2086677963544759, "edge_color": "rgb(255,255,255)", "edge_trans": 0.2, "edge_thick": 1.0}}, {"data": {"source": "TRT", "target": "TRT Change", "weight": -0.20874974217975117, "edge_color": "rgb(255,255,255)", "edge_trans": 0.2, "edge_thick": 1.0}}, {"data": {"source": "TRT", "target": "GCIPL", "weight": 0.8893088356749427, "edge_color": "rgb(28,28,28)", "edge_trans": 0.7335853602914713, "edge_thick": 3.667926801457356}}, {"data": {"source": "TRT", "target": "GCIPL Change", "weight": -0.21015868156082987, "edge_color": "rgb(255,255,255)", "edge_trans": 0.2, "edge_thick": 1.0}}, {"data": {"source": "TRT", "target": "ORL Change", "weight": -0.1668697508273581, "edge_color": "rgb(255,255,255)", "edge_trans": 0.2, "edge_thick": 1.0}}, {"data": {"source": "TRT", "target": "T2LV Change", "weight": 0.1403887290942265, "edge_color": "rgb(220,220,220)", "edge_trans": 0.28423324675252104, "edge_thick": 1.421166233762605}}, {"data": {"source": "TRT", "target": "NBV", "weight": 0.20036193438148742, "edge_color": "rgb(204,204,204)", "edge_trans": 0.32021717389606547, "edge_thick": 1.6010858694803272}}, {"data": {"source": "TRT", "target": "NBV Change", "weight": -0.17946721871274807, "edge_color": "rgb(255,255,255)", "edge_trans": 0.2, "edge_thick": 1.0}}, {"data": {"source": "TMV", "target": "mRNFL", "weight": 0.3898993836170929, "edge_color": "rgb(156,156,156)", "edge_trans": 0.43393965598784734, "edge_thick": 2.169698279939236}}, {"data": {"source": "TMV", "target": "TMV Change", "weight": -0.2086614620712271, "edge_color": "rgb(255,255,255)", "edge_trans": 0.2, "edge_thick": 1.0}}, {"data": {"source": "TMV", "target": "TRT Change", "weight": -0.2087421502069553, "edge_color": "rgb(255,255,255)", "edge_trans": 0.2, "edge_thick": 1.0}}, {"data": {"source": "TMV", "target": "GCIPL", "weight": 0.8893176919380281, "edge_color": "rgb(28,28,28)", "edge_trans": 0.733590674049909, "edge_thick": 3.6679533702495446}}, {"data": {"source": "TMV", "target": "GCIPL Change", "weight": -0.21014700470825956, "edge_color": "rgb(255,255,255)", "edge_trans": 0.2, "edge_thick": 1.0}}, {"data": {"source": "TMV", "target": "ORL Change", "weight": -0.166869815881422, "edge_color": "rgb(255,255,255)", "edge_trans": 0.2, "edge_thick": 1.0}}, {"data": {"source": "TMV", "target": "T2LV Change", "weight": 0.14034948589235596, "edge_color": "rgb(220,220,220)", "edge_trans": 0.28420970082880015, "edge_thick": 1.4210485041440006}}, {"data": {"source": "TMV", "target": "NBV", "weight": 0.20038693002815933, "edge_color": "rgb(204,204,204)", "edge_trans": 0.32023217128572373, "edge_thick": 1.6011608564286184}}, {"data": {"source": "TMV", "target": "NBV Change", "weight": -0.17944706781783498, "edge_color": "rgb(255,255,255)", "edge_trans": 0.2, "edge_thick": 1.0}}, {"data": {"source": "T2LV Change", "target": "GCIPL Change", "weight": -0.14502844762425177, "edge_color": "rgb(255,255,255)", "edge_trans": 0.2, "edge_thick": 1.0}}, {"data": {"source": "T2LV Change", "target": "T2LC Change", "weight": 0.42318958639917337, "edge_color": "rgb(147,147,147)", "edge_trans": 0.4539137798614408, "edge_thick": 2.269568899307204}}, {"data": {"source": "T2LV Change", "target": "NBV", "weight": 0.186930282369807, "edge_color": "rgb(208,208,208)", "edge_trans": 0.3121581817996665, "edge_thick": 1.560790908998332}}, {"data": {"source": "T2LV Change", "target": "NBV Change", "weight": -0.14650079358072127, "edge_color": "rgb(255,255,255)", "edge_trans": 0.2, "edge_thick": 1.0}}, {"data": {"source": "T2LC Change", "target": "GCIPL Change", "weight": -0.14847613513503047, "edge_color": "rgb(255,255,255)", "edge_trans": 0.2, "edge_thick": 1.0}}, {"data": {"source": "T2LC Change", "target": "NBV", "weight": 0.1603119731112449, "edge_color": "rgb(214,214,214)", "edge_trans": 0.2961871944819703, "edge_thick": 1.4809359724098514}}, {"data": {"source": "T2LC Change", "target": "NBV Change", "weight": -0.1350666111325025, "edge_color": "rgb(255,255,255)", "edge_trans": 0.2, "edge_thick": 1.0}}, {"data": {"source": "T2LC Change", "target": "NWMV Change", "weight": -0.13962781859874598, "edge_color": "rgb(255,255,255)", "edge_trans": 0.2, "edge_thick": 1.0}}, {"data": {"source": "NBV", "target": "mRNFL", "weight": 0.18593383664080076, "edge_color": "rgb(208,208,208)", "edge_trans": 0.31156031429628206, "edge_thick": 1.5578015714814102}}, {"data": {"source": "NBV", "target": "GCIPL", "weight": 0.27045134572471685, "edge_color": "rgb(186,186,186)", "edge_trans": 0.3622708253430461, "edge_thick": 1.8113541267152304}}, {"data": {"source": "NBV", "target": "T2LC", "weight": -0.3420973190567883, "edge_color": "rgb(255,255,255)", "edge_trans": 0.2, "edge_thick": 1.0}}, {"data": {"source": "NBV", "target": "T2LV", "weight": -0.42093586387200665, "edge_color": "rgb(255,255,255)", "edge_trans": 0.2, "edge_thick": 1.0}}, {"data": {"source": "NBV", "target": "NBV Change", "weight": -0.6251737790764196, "edge_color": "rgb(255,255,255)", "edge_trans": 0.2, "edge_thick": 1.0}}, {"data": {"source": "NBV", "target": "NWMV Change", "weight": -0.3626874214743447, "edge_color": "rgb(255,255,255)", "edge_trans": 0.2, "edge_thick": 1.0}}, {"data": {"source": "NBV", "target": "NGMV", "weight": 0.6223838903333727, "edge_color": "rgb(96,96,96)", "edge_trans": 0.5734303754118176, "edge_thick": 2.8671518770590874}}, {"data": {"source": "NBV", "target": "NGMV Change", "weight": -0.1517690829835149, "edge_color": "rgb(255,255,255)", "edge_trans": 0.2, "edge_thick": 1.0}}, {"data": {"source": "TRT Change", "target": "TMV Change", "weight": 0.9999937945877215, "edge_color": "rgb(0,0,0)", "edge_trans": 0.7999963429682577, "edge_thick": 3.9999817148412884}}, {"data": {"source": "TRT Change", "target": "GCIPL", "weight": -0.16845403104360024, "edge_color": "rgb(255,255,255)", "edge_trans": 0.2, "edge_thick": 1.0}}, {"data": {"source": "TRT Change", "target": "GCIPL Change", "weight": 0.24412018166045946, "edge_color": "rgb(193,193,193)", "edge_trans": 0.3464721251609464, "edge_thick": 1.7323606258047317}}, {"data": {"source": "TRT Change", "target": "ORL Change", "weight": 0.7217733740037888, "edge_color": "rgb(71,71,71)", "edge_trans": 0.633064072195245, "edge_thick": 3.1653203609762244}}, {"data": {"source": "TMV Change", "target": "GCIPL", "weight": -0.16834586793070394, "edge_color": "rgb(255,255,255)", "edge_trans": 0.2, "edge_thick": 1.0}}, {"data": {"source": "TMV Change", "target": "GCIPL Change", "weight": 0.24390034459576077, "edge_color": "rgb(193,193,193)", "edge_trans": 0.3463402229075704, "edge_thick": 1.7317011145378518}}, {"data": {"source": "TMV Change", "target": "ORL Change", "weight": 0.7217892700249154, "edge_color": "rgb(71,71,71)", "edge_trans": 0.6330736098089734, "edge_thick": 3.165368049044867}}, {"data": {"source": "T2LV", "target": "mRNFL", "weight": -0.30965280133917944, "edge_color": "rgb(255,255,255)", "edge_trans": 0.2, "edge_thick": 1.0}}, {"data": {"source": "T2LV", "target": "T2LC", "weight": 0.5252707011444133, "edge_color": "rgb(121,121,121)", "edge_trans": 0.5151624554679916, "edge_thick": 2.575812277339957}}, {"data": {"source": "T2LV", "target": "NGMV", "weight": -0.5101775834179968, "edge_color": "rgb(255,255,255)", "edge_trans": 0.2, "edge_thick": 1.0}}, {"data": {"source": "T2LV", "target": "NGMV Change", "weight": 0.3116527437835067, "edge_color": "rgb(176,176,176)", "edge_trans": 0.3869916669065133, "edge_thick": 1.934958334532566}}, {"data": {"source": "NGMV Change", "target": "mRNFL", "weight": -0.3231929723670872, "edge_color": "rgb(255,255,255)", "edge_trans": 0.2, "edge_thick": 1.0}}, {"data": {"source": "NGMV Change", "target": "NWMV Change", "weight": -0.6637416357771635, "edge_color": "rgb(255,255,255)", "edge_trans": 0.2, "edge_thick": 1.0}}, {"data": {"source": "NGMV Change", "target": "NGMV", "weight": -0.664020296231717, "edge_color": "rgb(255,255,255)", "edge_trans": 0.2, "edge_thick": 1.0}}, {"data": {"source": "NGMV", "target": "mRNFL", "weight": 0.344251629174986, "edge_color": "rgb(167,167,167)", "edge_trans": 0.4065510002999698, "edge_thick": 2.032755001499849}}, {"data": {"source": "NGMV", "target": "T2LC", "weight": -0.2521138049623665, "edge_color": "rgb(255,255,255)", "edge_trans": 0.2, "edge_thick": 1.0}}, {"data": {"source": "NGMV", "target": "NWMV Change", "weight": 0.3591272601975972, "edge_color": "rgb(163,163,163)", "edge_trans": 0.41547637989854186, "edge_thick": 2.077381899492709}}, {"data": {"source": "mRNFL", "target": "GCIPL", "weight": 0.2378110514180623, "edge_color": "rgb(195,195,195)", "edge_trans": 0.3426866465977425, "edge_thick": 1.7134332329887123}}, {"data": {"source": "mRNFL", "target": "T2LC", "weight": -0.1865762626997625, "edge_color": "rgb(255,255,255)", "edge_trans": 0.2, "edge_thick": 1.0}}, {"data": {"source": "mRNFL", "target": "NWMV Change", "weight": 0.2015362373544617, "edge_color": "rgb(204,204,204)", "edge_trans": 0.32092175575760773, "edge_thick": 1.6046087787880385}}, {"data": {"source": "ORL Change", "target": "GCIPL Change", "weight": -0.2141454118235094, "edge_color": "rgb(255,255,255)", "edge_trans": 0.2, "edge_thick": 1.0}}, {"data": {"source": "ORL Change", "target": "T2LC", "weight": 0.16074225135714884, "edge_color": "rgb(214,214,214)", "edge_trans": 0.296445361458004, "edge_thick": 1.4822268072900198}}, {"data": {"source": "NBV Change", "target": "GCIPL", "weight": -0.24854159512891208, "edge_color": "rgb(255,255,255)", "edge_trans": 0.2, "edge_thick": 1.0}}, {"data": {"source": "NBV Change", "target": "T2LC", "weight": 0.1468644947862106, "edge_color": "rgb(218,218,218)", "edge_trans": 0.288118706596511, "edge_thick": 1.440593532982555}}, {"data": {"source": "NBV Change", "target": "NWMV Change", "weight": 0.7369125024445002, "edge_color": "rgb(66,66,66)", "edge_trans": 0.6421475502621248, "edge_thick": 3.2107377513106234}}, {"data": {"source": "NWMV Change", "target": "GCIPL", "weight": -0.15292541194192133, "edge_color": "rgb(255,255,255)", "edge_trans": 0.2, "edge_thick": 1.0}}, {"data": {"source": "GCIPL Change", "target": "GCIPL", "weight": -0.3771058761662376, "edge_color": "rgb(255,255,255)", "edge_trans": 0.2, "edge_thick": 1.0}}]